README.md
setup.cfg
setup.py
pyticker/__init__.py
pyticker/pyticker_main.py
pyticker.egg-info/PKG-INFO
pyticker.egg-info/SOURCES.txt
pyticker.egg-info/dependency_links.txt
pyticker.egg-info/entry_points.txt
pyticker.egg-info/requires.txt
pyticker.egg-info/top_level.txt
pyticker/core/__init__.py
pyticker/core/positions.py
pyticker/core/pyticker_db_operations.py
pyticker/core/util.py
pyticker/core/yahoo_client.py
pyticker/core/yahoo_response_model.py
pyticker/view/__init__.py
pyticker/view/bottom_input_instructions_view.py
pyticker/view/positions_view.py
pyticker/view/pyticker_layout.py
pyticker/view/pyticker_styles.py
pyticker/view/watchlist_view.py
tests/__init__.py
tests/pyticker_db_operations_test.py
tests/yahoo_client_test.py