Metadata-Version: 2.1
Name: pyticker
Version: 1.4
Summary: Terminal based stocks and portfolio tracks.
Home-page: https://github.com/priyanshus/pyticker
License: MIT
Keywords: terminal-app finance stocks ticker
Platform: UNKNOWN
Classifier: Development Status :: 3 - Alpha
Classifier: Intended Audience :: Information Technology
Classifier: License :: OSI Approved :: MIT License
Classifier: Programming Language :: Python :: 3.8
Requires-Python: >=3.8
